bluebell/__init__.py
bluebell/plot.py
bluebell-0.0.1.dist-info/LICENSE
bluebell-0.0.1.dist-info/METADATA
bluebell-0.0.1.dist-info/WHEEL
bluebell-0.0.1.dist-info/top_level.txt
bluebell-0.0.1.dist-info/RECORD
