Metadata-Version: 2.1
Name: bluebell
Version: 0.0.1
Summary: Basic linear uncertainty estimation with bounding ellipsoids
Home-page: https://github.com/warrickball/bluebell
Author: Warrick Ball
Author-email: W.H.Ball@bham.ac.uk
License: MIT
Download-URL: https://github.com/warrickball/bluebell/archive/v0.0.1.tar.gz
Platform: UNKNOWN
Classifier: Programming Language :: Python :: 3
Classifier: License :: OSI Approved :: MIT License
Classifier: Operating System :: OS Independent
Requires-Python: >=3.4
Requires-Dist: numpy
